easyverein/__init__.py
easyverein/api.py
easyverein/core/__init__.py
easyverein/core/client.py
easyverein/core/exceptions.py
easyverein/core/protocol.py
easyverein/core/responses.py
easyverein/core/types.py
easyverein/core/validators.py
easyverein/models/__init__.py
easyverein/models/base.py
easyverein/models/billing_account.py
easyverein/models/booking.py
easyverein/models/contact_details.py
easyverein/models/custom_field.py
easyverein/models/custom_field_select_option.py
easyverein/models/invoice.py
easyverein/models/invoice_item.py
easyverein/models/lsb_dosb_sport.py
easyverein/models/member.py
easyverein/models/member_custom_field.py
easyverein/models/member_group.py
easyverein/models/member_member_group.py
easyverein/models/mixins/__init__.py
easyverein/models/mixins/empty_strings_mixin.py
easyverein/models/mixins/required_attributes.py
easyverein/modules/__init__.py
easyverein/modules/billing_account.py
easyverein/modules/booking.py
easyverein/modules/contact_details.py
easyverein/modules/custom_field.py
easyverein/modules/custom_field_select_option.py
easyverein/modules/invoice.py
easyverein/modules/invoice_item.py
easyverein/modules/member.py
easyverein/modules/member_custom_field.py
easyverein/modules/member_group.py
easyverein/modules/member_member_group.py
easyverein/modules/mixins/__init__.py
easyverein/modules/mixins/crud.py
easyverein/modules/mixins/helper.py
easyverein/modules/mixins/recycle_bin.py
python_easyverein-2.3.0.dist-info/METADATA
python_easyverein-2.3.0.dist-info/WHEEL
python_easyverein-2.3.0.dist-info/licenses/LICENSE
python_easyverein-2.3.0.dist-info/RECORD
