Metadata-Version: 2.4
Name: python-easyverein
Version: 2.3.0
Summary: Python library to interact with the EasyVerein API
License: Copyright 2023 Daniel Herrmann
License-File: LICENSE
Author: Daniel Herrmann
Author-email: daniel.herrmann1@gmail.com
Requires-Python: >=3.11,<4
Classifier: License :: Other/Proprietary License
Classifier: Programming Language :: Python :: 3
Classifier: Programming Language :: Python :: 3.11
Classifier: Programming Language :: Python :: 3.12
Classifier: Programming Language :: Python :: 3.13
Classifier: Programming Language :: Python :: 3.14
Requires-Dist: email-validator (>=2,<3)
Requires-Dist: pydantic (>=2,<3)
Requires-Dist: requests (>=2,<3)
